PythonHeimofaShouceFix1/README.md
PythonHeimofaShouceFix1/__init__.py
PythonHeimofaShouceFix1/__main__.py
PythonHeimofaShouceFix1/file.epub
PythonHeimofaShouceFix1/index.html
PythonHeimofaShouceFix1/css/__init__.py
PythonHeimofaShouceFix1/css/annotations.css
PythonHeimofaShouceFix1/css/main.css
PythonHeimofaShouceFix1/css/normalize.css
PythonHeimofaShouceFix1/css/popup.css
PythonHeimofaShouceFix1/font/__init__.py
PythonHeimofaShouceFix1/font/fontello.eot
PythonHeimofaShouceFix1/font/fontello.svg
PythonHeimofaShouceFix1/font/fontello.ttf
PythonHeimofaShouceFix1/font/fontello.woff
PythonHeimofaShouceFix1/img/__init__.py
PythonHeimofaShouceFix1/img/annotator-glyph-sprite.png
PythonHeimofaShouceFix1/img/annotator-icon-sprite.png
PythonHeimofaShouceFix1/img/apple-touch-icon.png
PythonHeimofaShouceFix1/img/cancelfullscreen.png
PythonHeimofaShouceFix1/img/close.png
PythonHeimofaShouceFix1/img/fullscreen.png
PythonHeimofaShouceFix1/img/loader.gif
PythonHeimofaShouceFix1/img/menu-icon.png
PythonHeimofaShouceFix1/img/save.png
PythonHeimofaShouceFix1/img/saved.png
PythonHeimofaShouceFix1/img/settings-s.png
PythonHeimofaShouceFix1/img/settings.png
PythonHeimofaShouceFix1/img/star.png
PythonHeimofaShouceFix1/js/__init__.py
PythonHeimofaShouceFix1/js/epub.js
PythonHeimofaShouceFix1/js/epub.min.js
PythonHeimofaShouceFix1/js/epub.min.map
PythonHeimofaShouceFix1/js/hooks.min.js
PythonHeimofaShouceFix1/js/hooks.min.map
PythonHeimofaShouceFix1/js/reader.js
PythonHeimofaShouceFix1/js/reader.js.map
PythonHeimofaShouceFix1/js/reader.min.js
PythonHeimofaShouceFix1/js/reader.min.map
PythonHeimofaShouceFix1/js/hooks/__init__.py
PythonHeimofaShouceFix1/js/hooks/extensions/__init__.py
PythonHeimofaShouceFix1/js/hooks/extensions/highlight.js
PythonHeimofaShouceFix1/js/libs/__init__.py
PythonHeimofaShouceFix1/js/libs/jquery.min.js
PythonHeimofaShouceFix1/js/libs/localforage.min.js
PythonHeimofaShouceFix1/js/libs/screenfull.js
PythonHeimofaShouceFix1/js/libs/screenfull.min.js
python_heimofa_shouce_fix1-2025.3.25.1.dist-info/METADATA
python_heimofa_shouce_fix1-2025.3.25.1.dist-info/WHEEL
python_heimofa_shouce_fix1-2025.3.25.1.dist-info/entry_points.txt
python_heimofa_shouce_fix1-2025.3.25.1.dist-info/top_level.txt
python_heimofa_shouce_fix1-2025.3.25.1.dist-info/RECORD
